{
  "lesson_id": 33,
  "level_id": 18,
  "title": "Применение: Блиц-опрос клиентов",
  "description": "Блиц-опрос клиентов",
  "content": [
    {
      "question": "Какой артефакт используется на уровне 'Блиц-опрос клиентов'?",
      "options": [
        "5 ВОПРОСОВ ПО БОЛИ КЛИЕНТА",
        "Анкета клиента",
        "Форма обратной связи",
        "Отзывы"
      ],
      "explanation": "Артефакт этого уровня: 5 ВОПРОСОВ ПО БОЛИ КЛИЕНТА"
    }
  ],
  "video_url": "https://vimeo.com/1101188759",
  "duration_minutes": 7,
  "language": "ru",
  "version": "2.0",
  "created_at": "2025-10-09 12:00:00.000000+00",
  "updated_at": "2025-10-09 17:30:45.000000+00",
  "checksum_sha256": "57d2dca20970193492eabbaa3dcaf09e"
}